futar/__init__.py
bkkfutar-0.2.dist-info/LICENSE
bkkfutar-0.2.dist-info/METADATA
bkkfutar-0.2.dist-info/WHEEL
bkkfutar-0.2.dist-info/top_level.txt
bkkfutar-0.2.dist-info/RECORD
