Metadata-Version: 2.1
Name: bkkfutar
Version: 0.2
Summary: A simple client for BKK Futar API
Home-page: https://github.com/gabor-simon/bkk-futar-python-client
Author: Gabor Simon
Author-email: simonghun@gmail.com
License: UNKNOWN
Platform: UNKNOWN
Classifier: Programming Language :: Python :: 3
Classifier: License :: OSI Approved :: MIT License
Classifier: Operating System :: OS Independent
Requires-Python: >=3.6
Requires-Dist: requests
